{"nodes": [{"id": "ui_editor_inspector_tsx", "label": "Inspector.tsx", "file_type": "code", "source_file": "ui/editor/Inspector.tsx", "source_location": "L1"}, {"id": "inspector_getstableid", "label": "getStableId()", "file_type": "code", "source_file": "ui/editor/Inspector.tsx", "source_location": "L52"}, {"id": "inspector_isprimitivevalue", "label": "isPrimitiveValue()", "file_type": "code", "source_file": "ui/editor/Inspector.tsx", "source_location": "L56"}, {"id": "inspector_nodedatavalue", "label": "nodeDataValue()", "file_type": "code", "source_file": "ui/editor/Inspector.tsx", "source_location": "L64"}, {"id": "inspector_updatenodefield", "label": "updateNodeField()", "file_type": "code", "source_file": "ui/editor/Inspector.tsx", "source_location": "L68"}, {"id": "inspector_handleaddparam", "label": "handleAddParam()", "file_type": "code", "source_file": "ui/editor/Inspector.tsx", "source_location": "L730"}, {"id": "inspector_handleupdateparam", "label": "handleUpdateParam()", "file_type": "code", "source_file": "ui/editor/Inspector.tsx", "source_location": "L743"}, {"id": "inspector_handleremoveparam", "label": "handleRemoveParam()", "file_type": "code", "source_file": "ui/editor/Inspector.tsx", "source_location": "L749"}, {"id": "inspector_handletogglesection", "label": "handleToggleSection()", "file_type": "code", "source_file": "ui/editor/Inspector.tsx", "source_location": "L860"}], "edges": [{"source": "ui_editor_inspector_tsx", "target": "react", "relation": "imports_from", "confidence": "EXTRACTED", "source_file": "ui/editor/Inspector.tsx", "source_location": "L1", "weight": 1.0}, {"source": "ui_editor_inspector_tsx", "target": "ui_editor_store", "relation": "imports_from", "confidence": "EXTRACTED", "source_file": "ui/editor/Inspector.tsx", "source_location": "L2", "weight": 1.0}, {"source": "ui_editor_inspector_tsx", "target": "ui_editor_types", "relation": "imports_from", "confidence": "EXTRACTED", "source_file": "ui/editor/Inspector.tsx", "source_location": "L12", "weight": 1.0}, {"source": "ui_editor_inspector_tsx", "target": "ui_editor_audioengine", "relation": "imports_from", "confidence": "EXTRACTED", "source_file": "ui/editor/Inspector.tsx", "source_location": "L13", "weight": 1.0}, {"source": "ui_editor_inspector_tsx", "target": "ui_editor_nodehelpers", "relation": "imports_from", "confidence": "EXTRACTED", "source_file": "ui/editor/Inspector.tsx", "source_location": "L14", "weight": 1.0}, {"source": "ui_editor_inspector_tsx", "target": "ui_editor_handleids", "relation": "imports_from", "confidence": "EXTRACTED", "source_file": "ui/editor/Inspector.tsx", "source_location": "L15", "weight": 1.0}, {"source": "ui_editor_inspector_tsx", "target": "ui_editor_components_nodeshell", "relation": "imports_from", "confidence": "EXTRACTED", "source_file": "ui/editor/Inspector.tsx", "source_location": "L16", "weight": 1.0}, {"source": "ui_editor_inspector_tsx", "target": "ui_editor_codegenerator", "relation": "imports_from", "confidence": "EXTRACTED", "source_file": "ui/editor/Inspector.tsx", "source_location": "L22", "weight": 1.0}, {"source": "ui_editor_inspector_tsx", "target": "ui_editor_paramconnections", "relation": "imports_from", "confidence": "EXTRACTED", "source_file": "ui/editor/Inspector.tsx", "source_location": "L23", "weight": 1.0}, {"source": "ui_editor_inspector_tsx", "target": "ui_editor_nodeuiregistry", "relation": "imports_from", "confidence": "EXTRACTED", "source_file": "ui/editor/Inspector.tsx", "source_location": "L24", "weight": 1.0}, {"source": "ui_editor_inspector_tsx", "target": "ui_editor_uitokens", "relation": "imports_from", "confidence": "EXTRACTED", "source_file": "ui/editor/Inspector.tsx", "source_location": "L35", "weight": 1.0}, {"source": "ui_editor_inspector_tsx", "target": "ui_editor_nodecatalog_catalog", "relation": "imports_from", "confidence": "EXTRACTED", "source_file": "ui/editor/Inspector.tsx", "source_location": "L36", "weight": 1.0}, {"source": "ui_editor_inspector_tsx", "target": "ui_editor_studioporteditor", "relation": "imports_from", "confidence": "EXTRACTED", "source_file": "ui/editor/Inspector.tsx", "source_location": "L37", "weight": 1.0}, {"source": "ui_editor_inspector_tsx", "target": "inspector_getstableid", "relation": "contains", "confidence": "EXTRACTED", "source_file": "ui/editor/Inspector.tsx", "source_location": "L52", "weight": 1.0}, {"source": "ui_editor_inspector_tsx", "target": "inspector_isprimitivevalue", "relation": "contains", "confidence": "EXTRACTED", "source_file": "ui/editor/Inspector.tsx", "source_location": "L56", "weight": 1.0}, {"source": "ui_editor_inspector_tsx", "target": "inspector_nodedatavalue", "relation": "contains", "confidence": "EXTRACTED", "source_file": "ui/editor/Inspector.tsx", "source_location": "L64", "weight": 1.0}, {"source": "ui_editor_inspector_tsx", "target": "inspector_updatenodefield", "relation": "contains", "confidence": "EXTRACTED", "source_file": "ui/editor/Inspector.tsx", "source_location": "L68", "weight": 1.0}, {"source": "ui_editor_inspector_tsx", "target": "inspector_handleaddparam", "relation": "contains", "confidence": "EXTRACTED", "source_file": "ui/editor/Inspector.tsx", "source_location": "L730", "weight": 1.0}, {"source": "ui_editor_inspector_tsx", "target": "inspector_handleupdateparam", "relation": "contains", "confidence": "EXTRACTED", "source_file": "ui/editor/Inspector.tsx", "source_location": "L743", "weight": 1.0}, {"source": "ui_editor_inspector_tsx", "target": "inspector_handleremoveparam", "relation": "contains", "confidence": "EXTRACTED", "source_file": "ui/editor/Inspector.tsx", "source_location": "L749", "weight": 1.0}, {"source": "ui_editor_inspector_tsx", "target": "inspector_handletogglesection", "relation": "contains", "confidence": "EXTRACTED", "source_file": "ui/editor/Inspector.tsx", "source_location": "L860", "weight": 1.0}, {"source": "inspector_handleaddparam", "target": "inspector_getstableid", "relation": "calls", "confidence": "EXTRACTED", "source_file": "ui/editor/Inspector.tsx", "source_location": "L734", "weight": 1.0}]}